P8nImporter/__init__.py
P8nImporter/cli.py
P8nImporter/importer.py
P8nImporter/uploader.py
P8nImporter/api/__init__.py
P8nImporter/api/datasets.py
P8nImporter/config/__init__.py
P8nImporter/config/logging.py
P8nImporter/config/urls.py
P8nImporter/formats/__init__.py
P8nImporter/formats/asr_importer.py
P8nImporter/formats/base_importer.py
P8nImporter/formats/classification_importer.py
P8nImporter/formats/coco_json_importer.py
P8nImporter/formats/iam_importer.py
P8nImporter/formats/tabular_importer.py
P8nImporter/formats/voc_importer.py
P8nImporter/formats/yolov8_importer.py
P8nImporter/utilities/__init__.py
P8nImporter/utilities/api.py
P8nImporter/utilities/file.py
P8nImporter/utilities/importer.py
P8nImporter/utilities/keys.py
P8nImporter/utilities/mapping.py
P8nImporter/utilities/visualize.py
tests/__init__.py
p8n_importer-1.0.2.dist-info/LICENSE
p8n_importer-1.0.2.dist-info/METADATA
p8n_importer-1.0.2.dist-info/WHEEL
p8n_importer-1.0.2.dist-info/entry_points.txt
p8n_importer-1.0.2.dist-info/top_level.txt
p8n_importer-1.0.2.dist-info/RECORD
