Metadata-Version: 2.1
Name: p8n-importer
Version: 1.0.2
Summary: A tool to import various dataset formats and upload them to the PropulsionAI platform.
Home-page: https://www.propulsionhq.com/
Author: PropulsionAI
Author-email: hello@propulsionhq.com
Classifier: Programming Language :: Python :: 3
Classifier: Programming Language :: Python :: 3.7
Classifier: Programming Language :: Python :: 3.8
Classifier: Programming Language :: Python :: 3.10
Classifier: License :: OSI Approved :: MIT License
Classifier: Operating System :: OS Independent
Requires-Python: >=3.7
License-File: LICENSE
Requires-Dist: tqdm ==4.65.0
Requires-Dist: requests ==2.31.0
Requires-Dist: Pillow ==9.3.0
Requires-Dist: pyarrow
Requires-Dist: pandas
Requires-Dist: pyyaml
Requires-Dist: openpyxl
